zugh/__init__.py
zugh/db/__init__.py
zugh/db/connection.py
zugh/db/mysql.py
zugh/db/pool.py
zugh/db/query.py
zugh/query/__init__.py
zugh/query/aggregate.py
zugh/query/base.py
zugh/query/condition.py
zugh/query/core.py
zugh/query/filter.py
zugh/query/logic.py
zugh/query/math.py
zugh/query/others.py
zugh/query/string.py
zugh/schema/__init__.py
zugh/schema/db.py
zugh/schema/field.py
zugh/schema/table.py
zugh-0.0.1b3.dist-info/METADATA
zugh-0.0.1b3.dist-info/WHEEL
zugh-0.0.1b3.dist-info/top_level.txt
zugh-0.0.1b3.dist-info/RECORD
