Metadata-Version: 2.1
Name: zugh
Version: 0.0.1b3
Summary: Access to database flexibly
Home-page: https://github.com/StephenKwen/zugh
Author: StephenKwen
Author-email: hyuncankun@outlook.com
License: MIT
Keywords: SQL,MySQL
Platform: UNKNOWN
Classifier: Development Status :: 3 - Alpha
Classifier: Programming Language :: Python :: 3.6
Classifier: Programming Language :: Python :: 3.7
Classifier: Programming Language :: SQL
Classifier: License :: OSI Approved :: MIT License
Classifier: Operating System :: OS Independent
Requires-Python: >=3.6
Requires-Dist: PyMySQL (>=0.9.3)
